clusteval/__init__.py
clusteval/bubblegrid.py
clusteval/clusteval.py
clusteval/coord2density.py
clusteval/dbindex.py
clusteval/dbscan.py
clusteval/derivative.py
clusteval/examples.py
clusteval/hdbscan.py
clusteval/plot_dendrogram.py
clusteval/silhouette.py
clusteval/utils.py
clusteval-2.2.6.dist-info/licenses/LICENSE
clusteval-2.2.6.dist-info/METADATA
clusteval-2.2.6.dist-info/WHEEL
clusteval-2.2.6.dist-info/top_level.txt
clusteval-2.2.6.dist-info/RECORD
