Metadata-Version: 2.4
Name: clusteval
Version: 2.2.6
Summary: clusteval is a python package for unsupervised cluster validation.
Author-email: Erdogan Taskesen <erdogant@gmail.com>
License-Expression: MIT
Project-URL: Homepage, https://erdogant.github.io/clusteval
Project-URL: Download, https://github.com/erdogant/clusteval/archive/{version}.tar.gz
Keywords: Python,machine-learning,unsupervised,clustering,dbindex,silhouette score,density based clustering,validation
Classifier: Programming Language :: Python :: 3
Classifier: Operating System :: OS Independent
Classifier: Intended Audience :: Education
Classifier: Intended Audience :: Science/Research
Classifier: Operating System :: Unix
Classifier: Operating System :: Microsoft :: Windows
Classifier: Operating System :: MacOS
Classifier: Topic :: Scientific/Engineering :: Artificial Intelligence
Requires-Python: >=3
License-File: LICENSE
Requires-Dist: scatterd>=1.3.5
Requires-Dist: pypickle
Requires-Dist: matplotlib
Requires-Dist: numpy
Requires-Dist: pandas
Requires-Dist: tqdm
Requires-Dist: seaborn
Requires-Dist: scikit-learn
Requires-Dist: colourmap>=1.1.14
Requires-Dist: datazets>=1.1.0
Requires-Dist: df2onehot
Dynamic: license-file
